comments_bot/__init__.py
comments_bot/_utils.py
comments_bot/asyncClient.py
comments_bot/errors.py
comments_bot/syncClient.py
LICENSE
comments.bot-1.0.0.dist-info/LICENSE
comments.bot-1.0.0.dist-info/WHEEL
comments.bot-1.0.0.dist-info/METADATA
comments.bot-1.0.0.dist-info/RECORD
