Metadata-Version: 2.1
Name: comments.bot
Version: 1.0.0
Summary: A simple API wrapper for the comments.bot
Home-page: https://github.com/Divkix/comments.bot
License: MIT
Keywords: comments bot,comments.bot,comments.bot api
Author: Divkix
Author-email: techdroidroot@gmail.com
Requires-Python: >=3.6.2,<4.0.0
Classifier: Development Status :: 5 - Production/Stable
Classifier: License :: OSI Approved :: MIT License
Classifier: Operating System :: OS Independent
Classifier: Programming Language :: Python :: 3
Classifier: Programming Language :: Python :: 3.7
Classifier: Programming Language :: Python :: 3.8
Classifier: Programming Language :: Python :: 3.9
Classifier: Programming Language :: Python :: Implementation :: CPython
Classifier: Topic :: Software Development :: Libraries
Classifier: Topic :: Software Development :: Libraries :: Python Modules
Classifier: Topic :: Utilities
Requires-Dist: aiodns (>=3.0.0,<4.0.0)
Requires-Dist: aiohttp (>=3.7.4,<4.0.0)
Requires-Dist: cchardet (>=2.1.7,<3.0.0)
Requires-Dist: requests (>=2.25.1,<3.0.0)
Project-URL: Bug Tracker, https://github.com/Divkix/comments.bot/issues
Project-URL: Community, https://t.me/DivideProjects
Project-URL: Repository, https://github.com/Divkix/comments.bot
